[
  {
    "source": "UVM / Osher Center",
    "target": "P1"
  },
  {
    "source": "UVM / Osher Center",
    "target": "P2"
  },
  {
    "source": "UVM / Osher Center",
    "target": "P3"
  },
  {
    "source": "UVM / Osher Center",
    "target": "P4"
  },
  {
    "source": "UVM / Osher Center",
    "target": "P5"
  },
  {
    "source": "UVM / Osher Center",
    "target": "P6"
  },
  {
    "source": "UVM / Osher Center",
    "target": "P7"
  },
  {
    "source": "UVM / Osher Center",
    "target": "P8"
  },
  {
    "source": "UVM / Osher Center",
    "target": "P9"
  },
  {
    "source": "UVM / Osher Center",
    "target": "P10"
  },
  {
    "source": "UVM / Osher Center",
    "target": "P11"
  },
  {
    "source": "UVM / Osher Center",
    "target": "P12"
  },
  {
    "source": "UVM / Osher Center",
    "target": "P13"
  },
  {
    "source": "UVM / Osher Center",
    "target": "P14"
  },
  {
    "source": "UVM / Osher Center",
    "target": "P15"
  },
  {
    "source": "UVM / Osher Center",
    "target": "P16"
  },
  {
    "source": "UVM / Osher Center",
    "target": "P17"
  },
  {
    "source": "UVM / Osher Center",
    "target": "P18"
  },
  {
    "source": "UVM / Osher Center",
    "target": "P19"
  },
  {
    "source": "UVM / Osher Center",
    "target": "P20"
  },
  {
    "source": "UVM / Osher Center",
    "target": "P21"
  },
  {
    "source": "UVM / Osher Center",
    "target": "P22"
  },
  {
    "source": "UVM / Osher Center",
    "target": "P23"
  },
  {
    "source": "UVM / Osher Center",
    "target": "P24"
  },
  {
    "source": "UVM / Osher Center",
    "target": "P25"
  },
  {
    "source": "UVM / Osher Center",
    "target": "P26"
  },
  {
    "source": "UVM / Osher Center",
    "target": "P27"
  },
  {
    "source": "UVM / Osher Center",
    "target": "P28"
  },
  {
    "source": "UVM / Osher Center",
    "target": "P30"
  },
  {
    "source": "UVM / Osher Center / Employee Welness (UVM)",
    "target": "P17"
  },
  {
    "source": "UVM / CHWB",
    "target": "P1"
  },
  {
    "source": "UVM / CHWB",
    "target": "P19"
  },
  {
    "source": "UVM / Gund",
    "target": "P9"
  },
  {
    "source": "UVM / Complex Systems",
    "target": "P1"
  },
  {
    "source": "UVM / CNHS / RMS / Health Coaching",
    "target": "P1"
  },
  {
    "source": "UVM / CNHS / RMS / Health Coaching",
    "target": "P3"
  },
  {
    "source": "UVM / CNHS / RMS / Health Coaching",
    "target": "P9"
  },
  {
    "source": "UVM / CNHS / RMS / Health Coaching",
    "target": "P10"
  },
  {
    "source": "UVM / CNHS / RMS / Health Coaching",
    "target": "P11"
  },
  {
    "source": "UVM / CNHS / RMS / Health Coaching",
    "target": "P12"
  },
  {
    "source": "UVM / CNHS / RMS / Health Coaching",
    "target": "P15"
  },
  {
    "source": "UVM / CNHS / RMS / Health Coaching",
    "target": "P16"
  },
  {
    "source": "UVM / CNHS / RMS / Health Coaching",
    "target": "P17"
  },
  {
    "source": "UVM / CNHS / RMS / Health Coaching",
    "target": "P18"
  },
  {
    "source": "UVM / CNHS / RMS / Health Coaching",
    "target": "P22"
  },
  {
    "source": "UVM / CNHS / RMS / Health Coaching",
    "target": "P26"
  },
  {
    "source": "UVM / CNHS / RMS / Health Coaching",
    "target": "P27"
  },
  {
    "source": "UVM / CNHS / Nursing",
    "target": "P22"
  },
  {
    "source": "UVM / CALS / CDAE",
    "target": "P11"
  },
  {
    "source": "UVM / CALS",
    "target": "P18"
  },
  {
    "source": "UVM / CASS / Psychology",
    "target": "P13"
  },
  {
    "source": "UVM / RSENR",
    "target": "P18"
  },
  {
    "source": "UVM / LCOM / Psychiatry (academic)",
    "target": "P2"
  },
  {
    "source": "UVM / LCOM / Psychiatry (academic)",
    "target": "P3"
  },
  {
    "source": "UVM / LCOM / Psychiatry (academic)",
    "target": "P4"
  },
  {
    "source": "UVM / LCOM / Psychiatry (academic)",
    "target": "P15"
  },
  {
    "source": "UVM / LCOM / Psychiatry (academic)",
    "target": "P17"
  },
  {
    "source": "UVM / LCOM / Psychiatry (academic)",
    "target": "P24"
  },
  {
    "source": "UVM / LCOM / Family Medicine (academic)",
    "target": "P2"
  },
  {
    "source": "UVM / LCOM / Family Medicine (academic)",
    "target": "P3"
  },
  {
    "source": "UVM / LCOM / Family Medicine (academic)",
    "target": "P12"
  },
  {
    "source": "UVM / LCOM / Family Medicine (academic)",
    "target": "P23"
  },
  {
    "source": "UVM / LCOM / Anastesiology (academic)",
    "target": "P14"
  },
  {
    "source": "UVM / LCOM / Medicine (academic)",
    "target": "P3"
  },
  {
    "source": "UVM / LCOM / Medicine (academic)",
    "target": "P15"
  },
  {
    "source": "UVM / LCOM / Emergency Med (academic)",
    "target": "P15"
  },
  {
    "source": "UVM / LCOM / Cancer Center (academic)",
    "target": "P8"
  },
  {
    "source": "UVM / CESS",
    "target": "P25"
  },
  {
    "source": "UVM / CEMS / BioMedical/Mechanical Eng",
    "target": "P20"
  },
  {
    "source": "UVMH / HR / Employee Wellness",
    "target": "P17"
  },
  {
    "source": "UVMH / Nutrtion/Culinary Medicine",
    "target": "P28"
  },
  {
    "source": "UVMH / Medical Group / Psychiatry (clinical) / Osher WH Division",
    "target": "P2"
  },
  {
    "source": "UVMH / Medical Group / Psychiatry (clinical) / Osher WH Division",
    "target": "P3"
  },
  {
    "source": "UVMH / Medical Group / Psychiatry (clinical) / Osher WH Division",
    "target": "P4"
  },
  {
    "source": "UVMH / Medical Group / Psychiatry (clinical) / Osher WH Division",
    "target": "P5"
  },
  {
    "source": "UVMH / Medical Group / Psychiatry (clinical) / Osher WH Division",
    "target": "P6"
  },
  {
    "source": "UVMH / Medical Group / Psychiatry (clinical) / Osher WH Division",
    "target": "P7"
  },
  {
    "source": "UVMH / Medical Group / Psychiatry (clinical) / Osher WH Division",
    "target": "P13"
  },
  {
    "source": "UVMH / Medical Group / Psychiatry (clinical) / Osher WH Division",
    "target": "P14"
  },
  {
    "source": "UVMH / Medical Group / Psychiatry (clinical) / Osher WH Division",
    "target": "P21"
  },
  {
    "source": "UVMH / Medical Group / Psychiatry (clinical) / Osher WH Division",
    "target": "P28"
  },
  {
    "source": "UVMH / Medical Group / Psychiatry (clinical) / Osher WH Division",
    "target": "P30"
  },
  {
    "source": "UVMH / Medical Group / Family Medicine (clinical)",
    "target": "P3"
  },
  {
    "source": "UVMH / Medical Group / Family Medicine (clinical)",
    "target": "P4"
  },
  {
    "source": "UVMH / Medical Group / Anastesiology (clinical)",
    "target": "P14"
  },
  {
    "source": "UVMH / Medical Group / Cancer Center (clinical)",
    "target": "P6"
  },
  {
    "source": "UVMH / Medical Group / Cancer Center (clinical)",
    "target": "P8"
  },
  {
    "source": "UVMH / Medical Group / Cancer Center (clinical)",
    "target": "P21"
  },
  {
    "source": "UVMH / Medical Group / Cancer Center (clinical)",
    "target": "P28"
  },
  {
    "source": "Dartmouth",
    "target": "P3"
  },
  {
    "source": "Dartmouth",
    "target": "P28"
  },
  {
    "source": "VT DOH",
    "target": "P16"
  },
  {
    "source": "Osher Collaborative / Wisconsin",
    "target": "P2"
  },
  {
    "source": "Osher Collaborative / Harvard",
    "target": "P2"
  },
  {
    "source": "ACIMH / WHITS",
    "target": "P4"
  },
  {
    "source": "DHVA / Medicaid",
    "target": "P7"
  },
  {
    "source": "BCBSVT",
    "target": "P2"
  },
  {
    "source": "BCBSVT",
    "target": "P4"
  },
  {
    "source": "PCORI",
    "target": "P10"
  },
  {
    "source": "NCCIH",
    "target": "P2"
  },
  {
    "source": "CMS",
    "target": "P3"
  },
  {
    "source": "SCUHS",
    "target": "P30"
  }
]
